{
    "O": [
        337,
        3857,
        858,
        4015
    ],
    "J": [
        319,
        2225,
        876,
        2783
    ],
    "M": [
        337,
        3393,
        858,
        3551
    ],
    "A": [
        519,
        15,
        637,
        95
    ],
    "F": [
        15,
        1457,
        537,
        1615
    ],
    "H": [
        51,
        1969,
        501,
        2079
    ],
    "C": [
        299,
        449,
        856,
        1007
    ],
    "K": [
        354,
        2929,
        841,
        3039
    ],
    "N": [
        373,
        3649,
        823,
        3759
    ],
    "Q": [
        337,
        4369,
        858,
        4527
    ],
    "D": [
        635,
        1737,
        1123,
        1847
    ],
    "B": [
        317,
        193,
        838,
        351
    ],
    "S": [
        544,
        4881,
        651,
        4961
    ],
    "L": [
        337,
        3137,
        858,
        3295
    ],
    "G": [
        15,
        1713,
        537,
        1871
    ],
    "E": [
        15,
        1153,
        537,
        1311
    ],
    "R": [
        337,
        4625,
        858,
        4783
    ],
    "P": [
        337,
        4113,
        858,
        4271
    ],
    "I": [
        641,
        1969,
        1118,
        2079
    ]
}