{
    "O": [
        622,
        3540,
        1112,
        4030
    ],
    "J": [
        695,
        2140,
        1038,
        2228
    ],
    "H": [
        522,
        1686,
        944,
        1813
    ],
    "E": [
        673,
        779,
        1061,
        867
    ],
    "A": [
        819,
        13,
        915,
        76
    ],
    "M": [
        522,
        3125,
        944,
        3252
    ],
    "C": [
        656,
        364,
        1078,
        491
    ],
    "U": [
        146,
        5873,
        568,
        6000
    ],
    "K": [
        641,
        2309,
        1092,
        2760
    ],
    "Q": [
        175,
        4499,
        539,
        4587
    ],
    "D": [
        656,
        572,
        1078,
        699
    ],
    "B": [
        656,
        157,
        1078,
        284
    ],
    "Y": [
        1082,
        5490,
        1169,
        5554
    ],
    "F": [
        663,
        948,
        1071,
        1036
    ],
    "L": [
        522,
        2879,
        944,
        3006
    ],
    "N": [
        656,
        3333,
        1078,
        3460
    ],
    "I": [
        522,
        1933,
        944,
        2060
    ],
    "S": [
        13,
        5458,
        435,
        5585
    ],
    "W": [
        900,
        4318,
        1351,
        4769
    ],
    "G": [
        641,
        1116,
        1093,
        1567
    ],
    "T": [
        72,
        5705,
        375,
        5793
    ],
    "R": [
        131,
        4888,
        583,
        5339
    ],
    "V": [
        932,
        4149,
        1318,
        4237
    ],
    "P": [
        174,
        4149,
        540,
        4237
    ],
    "Z": [
        1165,
        5050,
        1587,
        5177
    ],
    "X": [
        663,
        5031,
        1085,
        5196
    ]
}