{
    "J1": [
        180,
        5529,
        702,
        5734
    ],
    "D4": [
        15,
        2389,
        537,
        2546
    ],
    "J3": [
        180,
        6089,
        702,
        6246
    ],
    "I1": [
        150,
        5297,
        298,
        5406
    ],
    "G2": [
        180,
        4087,
        702,
        4244
    ],
    "A": [
        210,
        15,
        672,
        143
    ],
    "C1": [
        215,
        771,
        667,
        881
    ],
    "D1": [
        240,
        1717,
        642,
        1826
    ],
    "K": [
        243,
        6571,
        639,
        6650
    ],
    "J4": [
        162,
        6345,
        720,
        6473
    ],
    "D3": [
        185,
        2181,
        697,
        2290
    ],
    "G1": [
        180,
        3831,
        702,
        3988
    ],
    "C4": [
        162,
        1491,
        720,
        1619
    ],
    "I2": [
        397,
        5273,
        918,
        5430
    ],
    "C2": [
        180,
        979,
        702,
        1137
    ],
    "E": [
        139,
        2872,
        743,
        3476
    ],
    "F1": [
        362,
        3623,
        520,
        3732
    ],
    "J2": [
        180,
        5833,
        702,
        5990
    ],
    "B1": [
        162,
        241,
        720,
        369
    ],
    "G3": [
        162,
        4343,
        720,
        4471
    ],
    "D5": [
        24,
        2693,
        528,
        2773
    ],
    "D2": [
        180,
        1925,
        702,
        2082
    ],
    "B2": [
        180,
        467,
        702,
        673
    ],
    "C3": [
        180,
        1235,
        702,
        1392
    ],
    "L": [
        138,
        6749,
        744,
        6925
    ],
    "H": [
        163,
        4570,
        719,
        5126
    ]
}