{
    "J": [
        281,
        2515,
        715,
        2624
    ],
    "H": [
        331,
        1777,
        666,
        2112
    ],
    "E": [
        296,
        1361,
        700,
        1470
    ],
    "A": [
        521,
        15,
        984,
        143
    ],
    "M": [
        273,
        3139,
        723,
        3248
    ],
    "C": [
        515,
        449,
        990,
        559
    ],
    "Q": [
        238,
        4307,
        759,
        4464
    ],
    "K": [
        274,
        2723,
        722,
        2832
    ],
    "D": [
        474,
        657,
        1031,
        1215
    ],
    "B": [
        560,
        241,
        946,
        351
    ],
    "F": [
        799,
        1361,
        1215,
        1470
    ],
    "L": [
        267,
        2931,
        729,
        3040
    ],
    "N": [
        220,
        3347,
        777,
        3904
    ],
    "I": [
        413,
        2259,
        934,
        2416
    ],
    "G": [
        270,
        1569,
        727,
        1678
    ],
    "P": [
        518,
        4051,
        1039,
        4208
    ],
    "R": [
        267,
        4563,
        729,
        4690
    ],
    "O": [
        15,
        4075,
        419,
        4184
    ]
}