{
    "H": [
        0,
        891,
        1600,
        892
    ],
    "J": [
        0,
        891,
        1600,
        892
    ],
    "U": [
        0,
        891,
        1600,
        892
    ],
    "E": [
        0,
        891,
        1600,
        892
    ],
    "O": [
        0,
        891,
        1600,
        892
    ],
    "A": [
        0,
        891,
        1600,
        892
    ],
    "C": [
        0,
        891,
        1600,
        892
    ],
    "M": [
        0,
        891,
        1600,
        892
    ],
    "Q": [
        0,
        891,
        1600,
        892
    ],
    "L": [
        0,
        891,
        1600,
        892
    ],
    "S": [
        0,
        891,
        1600,
        892
    ],
    "D": [
        0,
        891,
        1600,
        892
    ],
    "B": [
        0,
        891,
        1600,
        892
    ],
    "I": [
        0,
        891,
        1600,
        892
    ],
    "K": [
        0,
        891,
        1600,
        892
    ],
    "F": [
        0,
        891,
        1600,
        892
    ],
    "N": [
        0,
        891,
        1600,
        892
    ],
    "T": [
        0,
        891,
        1600,
        892
    ],
    "V": [
        0,
        891,
        1600,
        892
    ],
    "P": [
        0,
        891,
        1600,
        892
    ],
    "G": [
        0,
        891,
        1600,
        892
    ],
    "R": [
        0,
        891,
        1600,
        892
    ]
}