{
    "E": [
        0,
        4605,
        1208,
        4606
    ],
    "A": [
        0,
        4605,
        1208,
        4606
    ],
    "O": [
        0,
        4605,
        1208,
        4606
    ],
    "H": [
        0,
        4605,
        1208,
        4606
    ],
    "C": [
        0,
        4605,
        1208,
        4606
    ],
    "K": [
        0,
        4605,
        1208,
        4606
    ],
    "D": [
        0,
        4605,
        1208,
        4606
    ],
    "B": [
        0,
        4605,
        1208,
        4606
    ],
    "F": [
        0,
        4605,
        1208,
        4606
    ],
    "N": [
        0,
        4605,
        1208,
        4606
    ],
    "G": [
        0,
        4605,
        1208,
        4606
    ],
    "L": [
        0,
        4605,
        1208,
        4606
    ],
    "I": [
        0,
        4605,
        1208,
        4606
    ],
    "J": [
        0,
        4605,
        1208,
        4606
    ],
    "M": [
        0,
        4605,
        1208,
        4606
    ]
}