{
    "Start": [
        713,
        14,
        833,
        96
    ],
    "RecursiveSubclassLoop": [
        290,
        2388,
        945,
        3044
    ],
    "SubclassRetrievalLoop": [
        445,
        418,
        1101,
        1074
    ],
    "InputClass": [
        493,
        192,
        1054,
        322
    ],
    "DecisionHasSubclass": [
        266,
        1540,
        969,
        2244
    ],
    "OutputC": [
        313,
        3236,
        922,
        3414
    ],
    "End": [
        718,
        1314,
        828,
        1395
    ],
    "OutputS": [
        13,
        1266,
        623,
        1444
    ]
}