{
    "S": [
        489,
        4136,
        875,
        4232
    ],
    "O": [
        391,
        3377,
        873,
        3858
    ],
    "H": [
        525,
        2314,
        974,
        2451
    ],
    "E": [
        13,
        2335,
        441,
        2430
    ],
    "A": [
        738,
        13,
        841,
        82
    ],
    "V": [
        481,
        5588,
        902,
        5684
    ],
    "C": [
        630,
        319,
        950,
        414
    ],
    "R": [
        755,
        5941,
        849,
        6010
    ],
    "W": [
        985,
        5568,
        1435,
        5704
    ],
    "U": [
        800,
        4920,
        1323,
        5443
    ],
    "K": [
        511,
        2713,
        753,
        2783
    ],
    "D": [
        549,
        497,
        1030,
        979
    ],
    "B": [
        658,
        166,
        921,
        235
    ],
    "Q": [
        559,
        3983,
        805,
        4053
    ],
    "F": [
        810,
        1103,
        1292,
        1584
    ],
    "N": [
        446,
        3199,
        818,
        3294
    ],
    "I": [
        971,
        1708,
        1453,
        2190
    ],
    "G": [
        762,
        2535,
        1038,
        2630
    ],
    "L": [
        448,
        2867,
        816,
        2962
    ],
    "M": [
        499,
        3045,
        765,
        3115
    ],
    "T": [
        820,
        4315,
        1302,
        4796
    ],
    "P": [
        625,
        5788,
        979,
        5857
    ],
    "J": [
        1138,
        2314,
        1587,
        2451
    ]
}