{
    "X": [
        0,
        6757,
        920,
        6758
    ],
    "E": [
        0,
        6757,
        920,
        6758
    ],
    "A": [
        0,
        6757,
        920,
        6758
    ],
    "H": [
        0,
        6757,
        920,
        6758
    ],
    "M": [
        0,
        6757,
        920,
        6758
    ],
    "C": [
        0,
        6757,
        920,
        6758
    ],
    "Q": [
        0,
        6757,
        920,
        6758
    ],
    "W": [
        0,
        6757,
        920,
        6758
    ],
    "S": [
        0,
        6757,
        920,
        6758
    ],
    "Z": [
        0,
        6757,
        920,
        6758
    ],
    "K": [
        0,
        6757,
        920,
        6758
    ],
    "U": [
        0,
        6757,
        920,
        6758
    ],
    "T": [
        0,
        6757,
        920,
        6758
    ],
    "D": [
        0,
        6757,
        920,
        6758
    ],
    "B": [
        0,
        6757,
        920,
        6758
    ],
    "F": [
        0,
        6757,
        920,
        6758
    ],
    "L": [
        0,
        6757,
        920,
        6758
    ],
    "N": [
        0,
        6757,
        920,
        6758
    ],
    "G": [
        0,
        6757,
        920,
        6758
    ],
    "I": [
        0,
        6757,
        920,
        6758
    ],
    "P": [
        0,
        6757,
        920,
        6758
    ],
    "R": [
        0,
        6757,
        920,
        6758
    ],
    "V": [
        0,
        6757,
        920,
        6758
    ],
    "O": [
        0,
        6757,
        920,
        6758
    ],
    "J": [
        0,
        6757,
        920,
        6758
    ]
}