{
    "J": [
        242,
        1828,
        574,
        1904
    ],
    "O": [
        438,
        2643,
        770,
        2975
    ],
    "H": [
        542,
        807,
        873,
        1139
    ],
    "M": [
        448,
        2384,
        758,
        2477
    ],
    "E": [
        561,
        470,
        854,
        517
    ],
    "A": [
        672,
        9,
        743,
        56
    ],
    "P": [
        263,
        3063,
        573,
        3156
    ],
    "Z": [
        383,
        4817,
        647,
        4864
    ],
    "C": [
        580,
        240,
        835,
        287
    ],
    "AF": [
        741,
        4817,
        992,
        4864
    ],
    "S": [
        664,
        3244,
        913,
        3291
    ],
    "Q": [
        316,
        3244,
        522,
        3291
    ],
    "AH": [
        1086,
        4817,
        1350,
        4864
    ],
    "AA": [
        1284,
        4923,
        1348,
        4970
    ],
    "K": [
        438,
        1963,
        770,
        2295
    ],
    "AC": [
        887,
        4191,
        1197,
        4283
    ],
    "D": [
        587,
        347,
        828,
        411
    ],
    "AJ": [
        1155,
        1828,
        1487,
        1904
    ],
    "B": [
        559,
        116,
        857,
        180
    ],
    "W": [
        9,
        4693,
        315,
        4758
    ],
    "Y": [
        375,
        4693,
        653,
        4758
    ],
    "F": [
        561,
        576,
        854,
        640
    ],
    "T": [
        623,
        3350,
        955,
        3682
    ],
    "N": [
        499,
        2536,
        708,
        2583
    ],
    "L": [
        1259,
        1227,
        1590,
        1559
    ],
    "I": [
        253,
        1648,
        563,
        1768
    ],
    "G": [
        578,
        700,
        837,
        747
    ],
    "AD": [
        911,
        4344,
        1173,
        4605
    ],
    "AE": [
        714,
        4693,
        1020,
        4758
    ],
    "AI": [
        1165,
        1647,
        1475,
        1769
    ],
    "AB": [
        974,
        3770,
        1307,
        4103
    ],
    "AG": [
        1080,
        4693,
        1357,
        4758
    ],
    "R": [
        633,
        3063,
        943,
        3156
    ],
    "V": [
        208,
        4343,
        469,
        4605
    ],
    "X": [
        37,
        4817,
        288,
        4864
    ],
    "U": [
        183,
        4191,
        493,
        4284
    ]
}