{
    "D3": [
        555,
        1787,
        783,
        1822
    ],
    "S": [
        1309,
        1776,
        1561,
        1833
    ],
    "O": [
        841,
        1974,
        981,
        2022
    ],
    "M": [
        830,
        1780,
        993,
        1829
    ],
    "E": [
        795,
        405,
        963,
        573
    ],
    "H": [
        1184,
        971,
        1330,
        1019
    ],
    "A": [
        716,
        8,
        768,
        42
    ],
    "F": [
        932,
        641,
        1100,
        809
    ],
    "C": [
        658,
        169,
        826,
        337
    ],
    "R": [
        1039,
        1787,
        1263,
        1822
    ],
    "K": [
        1169,
        1298,
        1344,
        1473
    ],
    "D2": [
        281,
        1787,
        510,
        1822
    ],
    "I": [
        1184,
        1088,
        1330,
        1136
    ],
    "N": [
        853,
        1879,
        969,
        1927
    ],
    "B": [
        630,
        88,
        854,
        124
    ],
    "Q": [
        1172,
        1540,
        1341,
        1709
    ],
    "G": [
        1184,
        877,
        1330,
        925
    ],
    "L": [
        842,
        1600,
        981,
        1648
    ],
    "J": [
        1184,
        1204,
        1330,
        1252
    ],
    "P": [
        1187,
        2068,
        1317,
        2116
    ],
    "T": [
        646,
        1886,
        693,
        1920
    ],
    "D1": [
        7,
        1787,
        236,
        1822
    ]
}