{
    "Y": [
        504,
        6136,
        977,
        6609
    ],
    "AB": [
        660,
        6922,
        1134,
        7031
    ],
    "M": [
        838,
        3362,
        1108,
        3632
    ],
    "E": [
        916,
        760,
        1389,
        1234
    ],
    "A": [
        956,
        12,
        1349,
        121
    ],
    "O": [
        284,
        3970,
        647,
        4334
    ],
    "S": [
        229,
        4848,
        702,
        5321
    ],
    "H": [
        758,
        1804,
        1232,
        1913
    ],
    "C": [
        973,
        394,
        1332,
        488
    ],
    "K": [
        698,
        2765,
        1037,
        2834
    ],
    "W": [
        12,
        5769,
        454,
        5904
    ],
    "Z": [
        1115,
        6731,
        1588,
        6840
    ],
    "N": [
        309,
        3754,
        622,
        3848
    ],
    "D": [
        916,
        570,
        1389,
        679
    ],
    "B": [
        916,
        203,
        1390,
        312
    ],
    "F": [
        774,
        1356,
        1216,
        1490
    ],
    "AC": [
        851,
        7113,
        944,
        7181
    ],
    "U": [
        500,
        5443,
        896,
        5537
    ],
    "AA": [
        432,
        6739,
        840,
        6832
    ],
    "Q": [
        55,
        4456,
        422,
        4550
    ],
    "R": [
        286,
        4632,
        645,
        4726
    ],
    "L": [
        706,
        2916,
        1030,
        3240
    ],
    "G": [
        738,
        1572,
        1253,
        1722
    ],
    "X": [
        415,
        5986,
        810,
        6054
    ],
    "I": [
        759,
        1994,
        1232,
        2468
    ],
    "V": [
        51,
        5619,
        416,
        5687
    ],
    "T": [
        48,
        5443,
        418,
        5537
    ],
    "P": [
        515,
        4456,
        891,
        4550
    ],
    "J": [
        698,
        2590,
        1038,
        2683
    ]
}